cli.py
reportobello.py
typst/packages/rpbl/util/0.0.1/main.typ
typst/packages/rpbl/util/0.0.1/typst.toml
typst/packages/rpbl/util/latest/main.typ
typst/packages/rpbl/util/latest/typst.toml
reportobello-0.2.6.dist-info/LICENSE
reportobello-0.2.6.dist-info/METADATA
reportobello-0.2.6.dist-info/WHEEL
reportobello-0.2.6.dist-info/entry_points.txt
reportobello-0.2.6.dist-info/top_level.txt
reportobello-0.2.6.dist-info/RECORD
