Metadata-Version: 2.1
Name: reportobello
Version: 0.2.6
Summary: Python SDK for the Reportobello API
Author: dosisod
License: LGPL-3.0-or-later
Project-URL: Source, https://github.com/reportobello/reportobello-python
Classifier: Intended Audience :: Developers
Classifier: License :: OSI Approved :: GNU Lesser General Public License v3 or later (LGPLv3+)
Classifier: Typing :: Typed
Requires-Python: >=3.9
License-File: LICENSE
Requires-Dist: httpx>=0.27.2
Requires-Dist: rich>=13.8.0
Requires-Dist: typst>=0.11.1
Requires-Dist: python-dotenv>=1.0.1
Requires-Dist: platformdirs>=4.3.6
